DESCRIPTION
LICENSE
MANIFEST.in
README
README.rst
setup.py
admin_display_fields_settings/__init__.py
admin_display_fields_settings/admin.py
admin_display_fields_settings/ajax.py
admin_display_fields_settings/forms.py
admin_display_fields_settings/http.py
admin_display_fields_settings/models.py
admin_display_fields_settings/settings.py
admin_display_fields_settings/tests.py
admin_display_fields_settings/urls.py
admin_display_fields_settings/utils.py
admin_display_fields_settings/static/admin_display_fields_settings/admin/css/admin_display_fields_settings.css
admin_display_fields_settings/static/admin_display_fields_settings/admin/js/admin_display_fields_settings.js
admin_display_fields_settings/static/admin_display_fields_settings/admin/js/jquery-ui.min.js
admin_display_fields_settings/templates/admin_display_fields_settings/admin/admin_display_fields_settings.html
admin_display_fields_settings/templates/admin_display_fields_settings/admin/includes/field.html
django_admin_display_fields_settings.egg-info/PKG-INFO
django_admin_display_fields_settings.egg-info/SOURCES.txt
django_admin_display_fields_settings.egg-info/dependency_links.txt
django_admin_display_fields_settings.egg-info/top_level.txt