Metadata-Version: 1.1
Name: django-admin-display-fields-settings
Version: 0.1.7
Summary: Django application. It adds a column view control form into admin area. You can choose which fields to display and sort them in the correct order for you. Possible fields for display are taken from ``list_display``. To sort the fields just drag the field into place.
